README.txt
setup.py
QooxdooCherrypyJsonRpc.egg-info/PKG-INFO
QooxdooCherrypyJsonRpc.egg-info/SOURCES.txt
QooxdooCherrypyJsonRpc.egg-info/dependency_links.txt
QooxdooCherrypyJsonRpc.egg-info/requires.txt
QooxdooCherrypyJsonRpc.egg-info/top_level.txt
qxcpjsonrpc/__init__.py
qxcpjsonrpc/access.py
qxcpjsonrpc/date.py
qxcpjsonrpc/error.py
qxcpjsonrpc/locator.py
qxcpjsonrpc/server.py
qxcpjsonrpc/test/__init__.py
qxcpjsonrpc/test/example.py
qxcpjsonrpc/test/suite.py
qxcpjsonrpc/test/fixture/binary
qxcpjsonrpc/test/fixture/text