Metadata-Version: 1.1
Name: QooxdooCherrypyJsonRpc
Version: 0.5.1
Summary: Qooxdoo-specific CherryPy-based JSON RPC-server
Home-page: https://bitbucket.org/saaj/qooxdoo-cherrypy-json-rpc
Author: saaj
Author-email: mail@saaj.me
License: LGPL-2.1+
Keywords: qooxdoo cherrypy javascript python rpc
Platform: Any
Classifier: Topic :: Communications
Classifier: Topic :: Software Development :: Libraries
Classifier: Framework :: CherryPy
Classifier: Programming Language :: Python :: 2.7
Classifier: Programming Language :: Python :: 3.3
Classifier: Intended Audience :: Developers
